procrusql/__init__.py
procrusql/parser.py
procrusql-0.0.17.dist-info/licenses/LICENSE
procrusql-0.0.17.dist-info/METADATA
procrusql-0.0.17.dist-info/WHEEL
procrusql-0.0.17.dist-info/entry_points.txt
procrusql-0.0.17.dist-info/top_level.txt
procrusql-0.0.17.dist-info/RECORD
