Metadata-Version: 2.4
Name: ProcruSQL
Version: 0.0.17
Summary: Make a database fit its description
Home-page: https://git.hjp.at:3000/hjp/procrusql
Author: Peter J. Holzer
Author-email: hjp@hjp.at
License: MIT
Project-URL: Bug Tracker, https://git.hjp.at:3000/hjp/procrusql/issues
Project-URL: Repository, https://git.hjp.at:3000/hjp/procrusql
Classifier: Programming Language :: Python :: 3
Classifier: Operating System :: OS Independent
Requires-Python: >=3.8
License-File: LICENSE
Dynamic: license-file
